flake8_prometheus_metrics_name/__init__.py
flake8_prometheus_metrics_name/api.py
flake8_prometheus_metrics_name/cheker.py
flake8_prometheus_metrics_name-0.1.14.dist-info/LICENSE
flake8_prometheus_metrics_name-0.1.14.dist-info/METADATA
flake8_prometheus_metrics_name-0.1.14.dist-info/WHEEL
flake8_prometheus_metrics_name-0.1.14.dist-info/entry_points.txt
flake8_prometheus_metrics_name-0.1.14.dist-info/RECORD
