Metadata-Version: 2.1
Name: flake8-prometheus-metrics-name
Version: 0.1.14
Summary: Flake8 plugin for prometheus metric name validation
Home-page: https://github.com/perminovs/flake8_prometheus_metrics_name
License: MIT
Keywords: flake8,linter,python,prometheus
Author: perminovs
Requires-Python: >=3.9.0,<4.0
Classifier: License :: OSI Approved :: MIT License
Classifier: Programming Language :: Python :: 3
Classifier: Programming Language :: Python :: 3.9
Classifier: Programming Language :: Python :: 3.10
Classifier: Programming Language :: Python :: 3.11
Requires-Dist: flake8 (>=7.1.1,<8.0.0)
Requires-Dist: prometheus_client (>=0.7.1,<=0.16.0)
Project-URL: Repository, https://github.com/perminovs/flake8_prometheus_metrics_name
